langgraph_gen/__init__.py
langgraph_gen/_version.py
langgraph_gen/cli.py
langgraph_gen/generate.py
langgraph_gen/assets/py-class-stub.j2
langgraph_gen/assets/py-impl-stub.j2
langgraph_gen/assets/py-stub-impl.j2
langgraph_gen/assets/py-stub-runtime-json.j2
langgraph_gen/assets/py-stub-runtime-yaml.j2
langgraph_gen/assets/py-stub.j2
langgraph_gen/assets/ts-stub-impl.j2
langgraph_gen/assets/ts-stub.j2
langgraph_gen-0.0.6.dist-info/METADATA
langgraph_gen-0.0.6.dist-info/WHEEL
langgraph_gen-0.0.6.dist-info/entry_points.txt
langgraph_gen-0.0.6.dist-info/licenses/LICENSE
langgraph_gen-0.0.6.dist-info/RECORD
