Metadata-Version: 2.4
Name: langgraph-gen
Version: 0.0.6
Summary: Genenerate code stubs for langgraph agents.
License-Expression: MIT
License-File: LICENSE
Requires-Python: >=3.9
Requires-Dist: jinja2>=3.1.5
Requires-Dist: langgraph>=0.2.74
Requires-Dist: pyyaml>=6.0.2
